wation/__init__.py
wation/cli.py
wation/collaborator.py
wation/wation.py
wation/modules/__init__.py
wation/modules/cli/__init__.py
wation/modules/cli/auth.py
wation/modules/cli/collab.py
wation/modules/cli/connection.py
wation/modules/cli/decoder.py
wation/modules/cli/encoder.py
wation/modules/cli/general.py
wation/modules/cli/hash.py
wation/modules/cli/hashid.py
wation/modules/cli/open.py
wation/modules/cli/profile.py
wation/modules/cli/update.py
wation/modules/cli/uuid.py
wation/modules/miscellaneous/__init__.py
wation/modules/miscellaneous/auth.py
wation/modules/miscellaneous/config.py
wation/modules/miscellaneous/file_handler.py
wation/modules/miscellaneous/server.py
wation-2.0.10.dist-info/METADATA
wation-2.0.10.dist-info/WHEEL
wation-2.0.10.dist-info/entry_points.txt
wation-2.0.10.dist-info/RECORD
