Metadata-Version: 2.3
Name: wation
Version: 2.0.10
Summary: This package provides a connector to interact with the services of wation.net
Project-URL: Homepage, https://github.com/TheWation
Author-email: Wation <Github@Wation.net>
License: MIT
Classifier: License :: OSI Approved :: MIT License
Classifier: Operating System :: OS Independent
Classifier: Programming Language :: Python :: 3
Requires-Python: >=3.5
Requires-Dist: appdirs
Requires-Dist: cryptography
Requires-Dist: requests
